[
    {
        "items": [
            {
                "id": 2,
                "name": "ChefMaster Stainless Steel Mixing Bowls",
                "quantity": 5120,
                "volume": 2000,
                "cover": 5
            },
            {
                "id": 27,
                "name": "Gatorade Thirst Quencher",
                "quantity": 3100,
                "volume": 400,
                "cover": 7
            },
            {
                "id": 24,
                "name": "Ben & Jerry's Chocolate Fudge Brownie Ice Cream",
                "quantity": 2200,
                "volume": 500,
                "cover": 5
            }
        ]
    }
]